license.txt
nose.cfg
pygoogledesktop.py
setup.py
simpleregistry.py
testPyGDS.py
xml2obj.py
PyGoogleDesktop.egg-info/PKG-INFO
PyGoogleDesktop.egg-info/SOURCES.txt
PyGoogleDesktop.egg-info/dependency_links.txt
PyGoogleDesktop.egg-info/requires.txt
PyGoogleDesktop.egg-info/top_level.txt
dist/PyGoogleDesktop-0.2-py2.5.egg
dist/PyGoogleDesktop-0.2.win32.exe
dist/PyGoogleDesktop-0.4-py2.5.egg
dist/PyGoogleDesktop-0.4.win32.exe
docs/Query API Developer Guide - Google Desktop APIs - Google Code.pdf
docs/apidoc.ini
docs/doc/api-objects.txt
docs/doc/class-tree.html
docs/doc/crarr.png
docs/doc/epydoc.css
docs/doc/epydoc.js
docs/doc/exceptions.AssertionError-class.html
docs/doc/frames.html
docs/doc/help.html
docs/doc/identifier-index.html
docs/doc/index.html
docs/doc/module-tree.html
docs/doc/pygoogledesktop-module.html
docs/doc/pygoogledesktop-pysrc.html
docs/doc/pygoogledesktop.PyGDS-class.html
docs/doc/redirect.html
docs/doc/simpleregistry-module.html
docs/doc/simpleregistry-pysrc.html
docs/doc/testPyGDS-module.html
docs/doc/testPyGDS-pysrc.html
docs/doc/testPyGDS.TestPyGDS-class.html
docs/doc/toc-everything.html
docs/doc/toc-pygoogledesktop-module.html
docs/doc/toc-simpleregistry-module.html
docs/doc/toc-testPyGDS-module.html
docs/doc/toc-xml2obj-module.html
docs/doc/toc.html
docs/doc/uml_class_diagram_for_exceptio.gif
docs/doc/uml_class_diagram_for_pygoogle.gif
docs/doc/uml_class_diagram_for_testpygd.gif
docs/doc/xml2obj-module.html
docs/doc/xml2obj-pysrc.html
