Metadata-Version: 1.0
Name: PyGoogleDesktop
Version: 0.4
Summary: This is a python interface into the Google Desktop Search Engine for Windows
Home-page: http://code.google.com/p/pythongoogledesktop
Author: Jack Atkinson
Author-email: doxalogos AT gmail dot com
License: BSD
Keywords: Google Desktop Search Engine
Platform: UNKNOWN
